unitysvc_services/__init__.py
unitysvc_services/cli.py
unitysvc_services/format_data.py
unitysvc_services/list.py
unitysvc_services/populate.py
unitysvc_services/publisher.py
unitysvc_services/py.typed
unitysvc_services/query.py
unitysvc_services/scaffold.py
unitysvc_services/update.py
unitysvc_services/utils.py
unitysvc_services/validator.py
unitysvc_services/models/__init__.py
unitysvc_services/models/base.py
unitysvc_services/models/listing_v1.py
unitysvc_services/models/provider_v1.py
unitysvc_services/models/seller_v1.py
unitysvc_services/models/service_v1.py
unitysvc_services-0.3.0.dist-info/licenses/LICENSE
unitysvc_services-0.3.0.dist-info/METADATA
unitysvc_services-0.3.0.dist-info/WHEEL
unitysvc_services-0.3.0.dist-info/entry_points.txt
unitysvc_services-0.3.0.dist-info/top_level.txt
unitysvc_services-0.3.0.dist-info/RECORD
