Metadata-Version: 2.4
Name: unitysvc-services
Version: 0.3.0
Summary: SDK for digital service providers on UnitySVC
Author-email: Bo Peng <bo.peng@unitysvc.com>
Maintainer-email: Bo Peng <bo.peng@unitysvc.com>
License-Expression: MIT
Project-URL: bugs, https://github.com/unitysvc/unitysvc-services/issues
Project-URL: changelog, https://github.com/unitysvc/unitysvc-services/blob/master/changelog.md
Project-URL: homepage, https://github.com/unitysvc/unitysvc-services
Requires-Python: >=3.11
License-File: LICENSE
Requires-Dist: typer
Requires-Dist: pydantic
Requires-Dist: email-validator
Requires-Dist: jsonschema
Requires-Dist: jinja2
Requires-Dist: rich
Requires-Dist: httpx
Requires-Dist: tomli-w
Provides-Extra: test
Requires-Dist: coverage; extra == "test"
Requires-Dist: pytest; extra == "test"
Requires-Dist: ruff; extra == "test"
Requires-Dist: mypy; extra == "test"
Requires-Dist: ipdb; extra == "test"
Provides-Extra: dev
Requires-Dist: coverage; extra == "dev"
Requires-Dist: pytest; extra == "dev"
Requires-Dist: ruff; extra == "dev"
Requires-Dist: ty; extra == "dev"
Requires-Dist: ipdb; extra == "dev"
Requires-Dist: mkdocs; extra == "dev"
Requires-Dist: mkdocs-material; extra == "dev"
Requires-Dist: mkdocs-autorefs; extra == "dev"
Provides-Extra: docs
Requires-Dist: mkdocs; extra == "docs"
Requires-Dist: mkdocs-material; extra == "docs"
Requires-Dist: mkdocs-autorefs; extra == "docs"
Dynamic: license-file
